{
  "metadata": {
    "domain": "mathematics",
    "curriculum": "AP Statistics",
    "view": "k12-prerequisites",
    "version": "0.1.0",
    "description": "AP Statistics topics with prerequisite ordering, colored by unit group",
    "sources": [
      "College Board AP Statistics Course and Exam Description"
    ],
    "last_updated": "2026-03-27"
  },
  "books": [
    {
      "id": "ap.stat.b1",
      "name": "Exploring Data",
      "color": "#ef4444",
      "order": 1
    },
    {
      "id": "ap.stat.b2",
      "name": "Sampling & Experimentation",
      "color": "#f97316",
      "order": 2
    },
    {
      "id": "ap.stat.b3",
      "name": "Probability & Distributions",
      "color": "#22c55e",
      "order": 3
    },
    {
      "id": "ap.stat.b4",
      "name": "Statistical Inference",
      "color": "#3b82f6",
      "order": 4
    },
    {
      "id": "ap.stat.b5",
      "name": "Advanced Inference & Regression",
      "color": "#8b5cf6",
      "order": 5
    }
  ],
  "nodes": [
    {
      "id": "ap.stat.categorical_data",
      "label": "Exploring Categorical Data",
      "type": "concept",
      "description": "Bar charts, pie charts, two-way tables, marginal and conditional distributions",
      "grade_range": ["AP"],
      "tags": ["subtopic"],
      "book": "ap.stat.b1",
      "bookName": "Exploring Data",
      "bookColor": "#ef4444",
      "bookOrder": 1
    },
    {
      "id": "ap.stat.quantitative_data",
      "label": "Exploring Quantitative Data",
      "type": "concept",
      "description": "Dotplots, histograms, stemplots, shape, center, spread",
      "grade_range": ["AP"],
      "tags": ["subtopic"],
      "book": "ap.stat.b1",
      "bookName": "Exploring Data",
      "bookColor": "#ef4444",
      "bookOrder": 1
    },
    {
      "id": "ap.stat.summary_statistics",
      "label": "Summary Statistics",
      "type": "concept",
      "description": "Mean, median, standard deviation, IQR, outliers, boxplots",
      "grade_range": ["AP"],
      "tags": ["subtopic"],
      "book": "ap.stat.b1",
      "bookName": "Exploring Data",
      "bookColor": "#ef4444",
      "bookOrder": 1
    },
    {
      "id": "ap.stat.normal_distribution",
      "label": "Normal Distribution",
      "type": "concept",
      "description": "Normal model, z-scores, empirical rule, normal probability calculations",
      "grade_range": ["AP"],
      "tags": ["subtopic"],
      "book": "ap.stat.b1",
      "bookName": "Exploring Data",
      "bookColor": "#ef4444",
      "bookOrder": 1
    },
    {
      "id": "ap.stat.scatterplots_correlation",
      "label": "Scatterplots & Correlation",
      "type": "concept",
      "description": "Scatterplots, correlation coefficient, describing bivariate relationships",
      "grade_range": ["AP"],
      "tags": ["subtopic"],
      "book": "ap.stat.b1",
      "bookName": "Exploring Data",
      "bookColor": "#ef4444",
      "bookOrder": 1
    },
    {
      "id": "ap.stat.linear_regression",
      "label": "Linear Regression",
      "type": "concept",
      "description": "Least-squares regression, residuals, r-squared, residual plots",
      "grade_range": ["AP"],
      "tags": ["subtopic"],
      "book": "ap.stat.b1",
      "bookName": "Exploring Data",
      "bookColor": "#ef4444",
      "bookOrder": 1
    },
    {
      "id": "ap.stat.sampling_methods",
      "label": "Sampling Methods",
      "type": "concept",
      "description": "SRS, stratified, cluster, systematic sampling; bias in sampling",
      "grade_range": ["AP"],
      "tags": ["subtopic"],
      "book": "ap.stat.b2",
      "bookName": "Sampling & Experimentation",
      "bookColor": "#f97316",
      "bookOrder": 2
    },
    {
      "id": "ap.stat.experiments",
      "label": "Designing Experiments",
      "type": "concept",
      "description": "Control, randomization, replication, blocking; observational vs. experimental",
      "grade_range": ["AP"],
      "tags": ["subtopic"],
      "book": "ap.stat.b2",
      "bookName": "Sampling & Experimentation",
      "bookColor": "#f97316",
      "bookOrder": 2
    },
    {
      "id": "ap.stat.probability",
      "label": "Probability Rules",
      "type": "concept",
      "description": "Basic probability, addition and multiplication rules, conditional probability",
      "grade_range": ["AP"],
      "tags": ["subtopic"],
      "book": "ap.stat.b3",
      "bookName": "Probability & Distributions",
      "bookColor": "#22c55e",
      "bookOrder": 3
    },
    {
      "id": "ap.stat.random_variables",
      "label": "Random Variables",
      "type": "concept",
      "description": "Discrete and continuous random variables, expected value, variance",
      "grade_range": ["AP"],
      "tags": ["subtopic"],
      "book": "ap.stat.b3",
      "bookName": "Probability & Distributions",
      "bookColor": "#22c55e",
      "bookOrder": 3
    },
    {
      "id": "ap.stat.binomial_geometric",
      "label": "Binomial & Geometric Distributions",
      "type": "concept",
      "description": "Binomial and geometric probability models, conditions, calculations",
      "grade_range": ["AP"],
      "tags": ["subtopic"],
      "book": "ap.stat.b3",
      "bookName": "Probability & Distributions",
      "bookColor": "#22c55e",
      "bookOrder": 3
    },
    {
      "id": "ap.stat.sampling_distributions",
      "label": "Sampling Distributions",
      "type": "concept",
      "description": "Sampling distribution of sample means and proportions, CLT",
      "grade_range": ["AP"],
      "tags": ["subtopic"],
      "book": "ap.stat.b3",
      "bookName": "Probability & Distributions",
      "bookColor": "#22c55e",
      "bookOrder": 3
    },
    {
      "id": "ap.stat.confidence_intervals_prop",
      "label": "Confidence Intervals for Proportions",
      "type": "concept",
      "description": "Constructing and interpreting confidence intervals for one and two proportions",
      "grade_range": ["AP"],
      "tags": ["subtopic"],
      "book": "ap.stat.b4",
      "bookName": "Statistical Inference",
      "bookColor": "#3b82f6",
      "bookOrder": 4
    },
    {
      "id": "ap.stat.confidence_intervals_mean",
      "label": "Confidence Intervals for Means",
      "type": "concept",
      "description": "Constructing and interpreting confidence intervals for one and two means (t-procedures)",
      "grade_range": ["AP"],
      "tags": ["subtopic"],
      "book": "ap.stat.b4",
      "bookName": "Statistical Inference",
      "bookColor": "#3b82f6",
      "bookOrder": 4
    },
    {
      "id": "ap.stat.hypothesis_tests_prop",
      "label": "Hypothesis Tests for Proportions",
      "type": "concept",
      "description": "Significance tests for one and two proportions",
      "grade_range": ["AP"],
      "tags": ["subtopic"],
      "book": "ap.stat.b4",
      "bookName": "Statistical Inference",
      "bookColor": "#3b82f6",
      "bookOrder": 4
    },
    {
      "id": "ap.stat.hypothesis_tests_mean",
      "label": "Hypothesis Tests for Means",
      "type": "concept",
      "description": "Significance tests for one and two means (t-tests), paired data",
      "grade_range": ["AP"],
      "tags": ["subtopic"],
      "book": "ap.stat.b4",
      "bookName": "Statistical Inference",
      "bookColor": "#3b82f6",
      "bookOrder": 4
    },
    {
      "id": "ap.stat.type_errors_power",
      "label": "Type I/II Errors & Power",
      "type": "concept",
      "description": "Type I and Type II errors, significance level, power of a test",
      "grade_range": ["AP"],
      "tags": ["subtopic"],
      "book": "ap.stat.b4",
      "bookName": "Statistical Inference",
      "bookColor": "#3b82f6",
      "bookOrder": 4
    },
    {
      "id": "ap.stat.chi_square",
      "label": "Chi-Square Tests",
      "type": "concept",
      "description": "Chi-square goodness of fit, independence, and homogeneity tests",
      "grade_range": ["AP"],
      "tags": ["subtopic"],
      "book": "ap.stat.b5",
      "bookName": "Advanced Inference & Regression",
      "bookColor": "#8b5cf6",
      "bookOrder": 5
    },
    {
      "id": "ap.stat.regression_inference",
      "label": "Inference for Regression",
      "type": "concept",
      "description": "Confidence intervals and significance tests for regression slope",
      "grade_range": ["AP"],
      "tags": ["subtopic"],
      "book": "ap.stat.b5",
      "bookName": "Advanced Inference & Regression",
      "bookColor": "#8b5cf6",
      "bookOrder": 5
    }
  ],
  "edges": [
    { "source": "ap.stat.categorical_data", "target": "ap.stat.quantitative_data", "relation": "prerequisite_for" },
    { "source": "ap.stat.quantitative_data", "target": "ap.stat.summary_statistics", "relation": "prerequisite_for" },
    { "source": "ap.stat.summary_statistics", "target": "ap.stat.normal_distribution", "relation": "prerequisite_for" },
    { "source": "ap.stat.quantitative_data", "target": "ap.stat.scatterplots_correlation", "relation": "prerequisite_for" },
    { "source": "ap.stat.scatterplots_correlation", "target": "ap.stat.linear_regression", "relation": "prerequisite_for" },
    { "source": "ap.stat.summary_statistics", "target": "ap.stat.linear_regression", "relation": "prerequisite_for" },
    { "source": "ap.stat.categorical_data", "target": "ap.stat.sampling_methods", "relation": "prerequisite_for" },
    { "source": "ap.stat.sampling_methods", "target": "ap.stat.experiments", "relation": "prerequisite_for" },
    { "source": "ap.stat.experiments", "target": "ap.stat.probability", "relation": "prerequisite_for" },
    { "source": "ap.stat.probability", "target": "ap.stat.random_variables", "relation": "prerequisite_for" },
    { "source": "ap.stat.random_variables", "target": "ap.stat.binomial_geometric", "relation": "prerequisite_for" },
    { "source": "ap.stat.normal_distribution", "target": "ap.stat.sampling_distributions", "relation": "prerequisite_for" },
    { "source": "ap.stat.random_variables", "target": "ap.stat.sampling_distributions", "relation": "prerequisite_for" },
    { "source": "ap.stat.sampling_distributions", "target": "ap.stat.confidence_intervals_prop", "relation": "prerequisite_for" },
    { "source": "ap.stat.sampling_distributions", "target": "ap.stat.confidence_intervals_mean", "relation": "prerequisite_for" },
    { "source": "ap.stat.confidence_intervals_prop", "target": "ap.stat.hypothesis_tests_prop", "relation": "prerequisite_for" },
    { "source": "ap.stat.confidence_intervals_mean", "target": "ap.stat.hypothesis_tests_mean", "relation": "prerequisite_for" },
    { "source": "ap.stat.hypothesis_tests_prop", "target": "ap.stat.type_errors_power", "relation": "prerequisite_for" },
    { "source": "ap.stat.hypothesis_tests_mean", "target": "ap.stat.type_errors_power", "relation": "prerequisite_for" },
    { "source": "ap.stat.hypothesis_tests_prop", "target": "ap.stat.chi_square", "relation": "prerequisite_for" },
    { "source": "ap.stat.categorical_data", "target": "ap.stat.chi_square", "relation": "prerequisite_for" },
    { "source": "ap.stat.linear_regression", "target": "ap.stat.regression_inference", "relation": "prerequisite_for" },
    { "source": "ap.stat.hypothesis_tests_mean", "target": "ap.stat.regression_inference", "relation": "prerequisite_for" },
    { "source": "ap.stat.binomial_geometric", "target": "ap.stat.sampling_distributions", "relation": "prerequisite_for" }
  ]
}
